easy_requp.py
easy_requp-0.1.1.dist-info/LICENSE
easy_requp-0.1.1.dist-info/METADATA
easy_requp-0.1.1.dist-info/WHEEL
easy_requp-0.1.1.dist-info/top_level.txt
easy_requp-0.1.1.dist-info/RECORD
