Metadata-Version: 2.1
Name: easy-requp
Version: 0.1.1
Summary: Easily manage Python packages based on requirements file specifications.
Home-page: https://github.com/lucatrv/easy-requp
Author: Luca Trevisani
Author-email: lucatrv@hotmail.com
License: UNKNOWN
Keywords: package manager pip requirements
Platform: UNKNOWN
Classifier: Development Status :: 5 - Production/Stable
Classifier: Intended Audience :: Developers
Classifier: Intended Audience :: End Users/Desktop
Classifier: Intended Audience :: System Administrators
Classifier: License :: OSI Approved :: GNU General Public License v3 or later (GPLv3+)
Classifier: Operating System :: OS Independent
Classifier: Programming Language :: Python
Classifier: Programming Language :: Python :: 3
Classifier: Programming Language :: Python :: 3 :: Only
Classifier: Programming Language :: Python :: 3.8
Classifier: Topic :: Software Development
Classifier: Topic :: System :: Installation/Setup
Classifier: Topic :: System :: Systems Administration
Classifier: Topic :: Utilities
Requires-Python: >=3.8
Requires-Dist: pip (>=10.0.0)
Requires-Dist: setuptools (>=26.1.0)
